MANIFEST.in
README.md
UNLICENSE
data247.py
setup.py
data247.egg-info/PKG-INFO
data247.egg-info/SOURCES.txt
data247.egg-info/dependency_links.txt
data247.egg-info/not-zip-safe
data247.egg-info/requires.txt
data247.egg-info/top_level.txt