Metadata-Version: 1.0
Name: data247
Version: 0.1
Summary: An API client for Data 24-7.
Home-page: https://github.com/rdegges/python-data247
Author: Randall Degges
Author-email: rdegges@gmail.com
License: UNLICENSE
Keywords: python data247
Platform: UNKNOWN
